slg_script_helpers/__init__.py
slg_script_helpers/helpers.py
slg_script_helpers-0.1.5.dist-info/METADATA
slg_script_helpers-0.1.5.dist-info/WHEEL
slg_script_helpers-0.1.5.dist-info/top_level.txt
slg_script_helpers-0.1.5.dist-info/RECORD
