Metadata-Version: 2.4
Name: slg-script-helpers
Version: 0.1.5
Summary: Helper functions for Python scripts including standardized config handling
Home-page: https://github.com/slgotting/script-helpers
Author: Steven Gotting
Author-email: sgotting21@gmail.com
Classifier: Programming Language :: Python :: 3
Classifier: License :: OSI Approved :: MIT License
Classifier: Operating System :: OS Independent
Requires-Python: >=3.6
Requires-Dist: pyyaml>=6.0
Dynamic: author
Dynamic: author-email
Dynamic: classifier
Dynamic: description
Dynamic: description-content-type
Dynamic: home-page
Dynamic: requires-dist
Dynamic: requires-python
Dynamic: summary
